{
    "$schema": "http://json-schema.org/draft-04/schema#",
    "_id": "kapi.tasks.remove_resp",
    "description": "AMQP API for tasks.remove_resp",
    "properties": {
        "Event-Category": {
            "enum": [
                "tasks"
            ],
            "type": "string"
        },
        "Event-Name": {
            "enum": [
                "remove_resp"
            ],
            "type": "string"
        },
        "Reply": {
            "type": "string"
        }
    },
    "required": [
        "Reply"
    ],
    "type": "object"
}
