{
    "$schema": "http://json-schema.org/draft-04/schema#",
    "_id": "system_config.notify.new_account",
    "description": "Schema for notify.new_account system_config",
    "properties": {
        "default_to": {
            "default": "",
            "description": "notify.new_account default to",
            "items": {
                "type": "string"
            },
            "type": "string"
        },
        "html_content_transfer_encoding": {
            "default": "7BIT",
            "description": "notify.new_account html content transfer encoding",
            "type": "string"
        },
        "text_content_transfer_encoding": {
            "default": "7BIT",
            "description": "notify.new_account text content transfer encoding",
            "type": "string"
        }
    },
    "type": "object"
}
